unitcalc/__init__.py
unitcalc/constants.py
unitcalc/physics.py
unitcalc/units.py
unitcalc/unit_parser/__init__.py
unitcalc/unit_parser/parse_units.py
unitcalc/value_types/__init__.py
unitcalc/value_types/value.py
unitcalc/value_types/base_values/__init__.py
unitcalc/value_types/base_values/current.py
unitcalc/value_types/base_values/distance.py
unitcalc/value_types/base_values/luminosity.py
unitcalc/value_types/base_values/mass.py
unitcalc/value_types/base_values/substance.py
unitcalc/value_types/base_values/temperature.py
unitcalc/value_types/base_values/time.py
unitcalc/value_types/complex_values/__init__.py
unitcalc/value_types/complex_values/charge.py
unitcalc/value_types/complex_values/electric_potential.py
unitcalc/value_types/complex_values/electric_resistance.py
unitcalc/value_types/complex_values/energy.py
unitcalc/value_types/complex_values/force.py
unitcalc/value_types/complex_values/power.py
unitcalc/value_types/complex_values/pressure.py
unitcalc-2.0.1.dist-info/LICENSE
unitcalc-2.0.1.dist-info/METADATA
unitcalc-2.0.1.dist-info/WHEEL
unitcalc-2.0.1.dist-info/top_level.txt
unitcalc-2.0.1.dist-info/RECORD
