Metadata-Version: 2.1
Name: unitcalc
Version: 2.0.1
Summary: A Python Library for doing Scientific/Engineering mathematics
Home-page: https://github.com/P-Contorta/UnitCalc
Author: Nicholas Armstrong
Author-email: nkarmstrong@ucdavis.edu
License: UNKNOWN
Keywords: SI,units,Science,Math,Engineering,Education,STEM
Platform: UNKNOWN
Classifier: Development Status :: 4 - Beta
Classifier: Intended Audience :: End Users/Desktop
Classifier: Intended Audience :: Science/Research
Classifier: License :: OSI Approved :: GNU General Public License v3 (GPLv3)
Classifier: Natural Language :: English
Classifier: Programming Language :: Python :: 3.6
Classifier: Programming Language :: Python :: 3.7
Classifier: Programming Language :: Python :: 3.8
Classifier: Programming Language :: Python :: 3.9
Classifier: Programming Language :: Python :: 3.10
Classifier: Topic :: Scientific/Engineering
Classifier: Topic :: Scientific/Engineering :: Astronomy
Classifier: Topic :: Scientific/Engineering :: Chemistry
Classifier: Topic :: Scientific/Engineering :: Mathematics
Classifier: Topic :: Scientific/Engineering :: Physics
Requires-Python: >=3.6
